compy/__init__.py
compy/compassrun.py
compy/compy_script.py
compy/utilities.py
compy-1.0.4.dist-info/LICENSE
compy-1.0.4.dist-info/METADATA
compy-1.0.4.dist-info/WHEEL
compy-1.0.4.dist-info/entry_points.txt
compy-1.0.4.dist-info/top_level.txt
compy-1.0.4.dist-info/RECORD
