Metadata-Version: 2.1
Name: compy
Version: 1.0.4
Summary: A package for reading CoMPASS directories into Python
Home-page: https://github.com/eaklein/compy
Author: E. A. Klein
Author-email: eklein@mit.edu
Project-URL: Bug Tracker, https://github.com/eaklein/compy/issues
Classifier: Programming Language :: Python :: 3
Classifier: License :: OSI Approved :: MIT License
Classifier: Operating System :: OS Independent
Requires-Python: >=3.6
License-File: LICENSE
Requires-Dist: xmltodict
Requires-Dist: click
Requires-Dist: imagingreso
Requires-Dist: matplotlib
Requires-Dist: numpy
Requires-Dist: pandas
Requires-Dist: scipy
Requires-Dist: python-dotenv
